{"id":"98505","mw":5,"date":"2025-09-20T16:30:00+00:00","ground":"Estadio de la Cerámica","home":{"id":"20","name":"Villarreal CF","score":2,"formation":null,"xi":[{"id":"1090228","name":"Júnior R.","num":1,"pos":null,"cap":false},{"id":"1090230","name":"A. Pedraza","num":24,"pos":null,"cap":false},{"id":"1090231","name":"Pau Navarro","num":26,"pos":null,"cap":false},{"id":"1090232","name":"Foyth","num":8,"pos":null,"cap":true},{"id":"1090229","name":"Rafa Marín","num":4,"pos":null,"cap":false},{"id":"1090233","name":"Gueye","num":18,"pos":null,"cap":false},{"id":"1090234","name":"I. Akhomach","num":11,"pos":null,"cap":false},{"id":"1090235","name":"A. Moleiro","num":20,"pos":null,"cap":false},{"id":"1090236","name":"T. Partey","num":16,"pos":null,"cap":false},{"id":"1090238","name":"Pepe","num":19,"pos":null,"cap":false},{"id":"1090237","name":"Mikautadze","num":9,"pos":null,"cap":false}],"bench":[{"id":"1090246","name":"Mouriño","num":15,"pos":null,"cap":false},{"id":"1090247","name":"Renato Veiga","num":12,"pos":null,"cap":false},{"id":"1090248","name":"Oluwaseyi","num":21,"pos":null,"cap":false},{"id":"1090249","name":"Santi C.v.","num":14,"pos":null,"cap":false},{"id":"1090239","name":"Solomon","num":6,"pos":null,"cap":false},{"id":"1090240","name":"Buchanan","num":17,"pos":null,"cap":false},{"id":"1090241","name":"Diego Conde","num":13,"pos":null,"cap":false},{"id":"1090242","name":"Arnau Tenas","num":25,"pos":null,"cap":false},{"id":"1090243","name":"A. Alti","num":3,"pos":null,"cap":false},{"id":"1090244","name":"S. Cardona","num":23,"pos":null,"cap":false},{"id":"1090245","name":"Parejo","num":10,"pos":null,"cap":false}]},"away":{"id":"13","name":"CA Osasuna","score":1,"formation":null,"xi":[{"id":"1090251","name":"S. Herrera","num":1,"pos":null,"cap":true},{"id":"1090252","name":"Catena","num":24,"pos":null,"cap":false},{"id":"1090253","name":"Juan Cruz","num":3,"pos":null,"cap":false},{"id":"1090254","name":"Boyomo","num":22,"pos":null,"cap":false},{"id":"1090255","name":"V. Rosier","num":19,"pos":null,"cap":false},{"id":"1090256","name":"Abel Bretones","num":23,"pos":null,"cap":false},{"id":"1090258","name":"Moncayola","num":7,"pos":null,"cap":false},{"id":"1090257","name":"Torró","num":6,"pos":null,"cap":false},{"id":"1090259","name":"Budimir","num":17,"pos":null,"cap":false},{"id":"1090260","name":"Víctor M.v.","num":21,"pos":null,"cap":false},{"id":"1090261","name":"Rubén García","num":14,"pos":null,"cap":false}],"bench":[{"id":"1090262","name":"A. Osambela","num":29,"pos":null,"cap":false},{"id":"1090263","name":"Herrando","num":5,"pos":null,"cap":false},{"id":"1090264","name":"Aitor Fdez.","num":13,"pos":null,"cap":false},{"id":"1090265","name":"I. Benito","num":2,"pos":null,"cap":false},{"id":"1090266","name":"S. Becker","num":18,"pos":null,"cap":false},{"id":"1090267","name":"Iker Muñoz","num":8,"pos":null,"cap":false},{"id":"1090268","name":"Raúl","num":9,"pos":null,"cap":false},{"id":"1090270","name":"Kike Barja","num":11,"pos":null,"cap":false},{"id":"1090269","name":"R. Chasco","num":34,"pos":null,"cap":false}]},"events":[{"min":32,"type":"yellow","team":"away","player":"V. Rosier"},{"min":38,"type":"yellow","team":"away","player":"Torró"},{"min":39,"type":"yellow","team":"away","player":"V. Rosier"},{"min":41,"type":"yellow","team":"home","player":"Pau Navarro"},{"min":50,"type":"pen","team":"away","player":"Budimir"},{"min":68,"type":"goal","team":"home","player":"Mikautadze"},{"min":84,"type":"goal","team":"home","player":"Gueye"},{"min":86,"type":"yellow","team":"home","player":"Santi C.v."}],"stats":[]}