{"id":"98741","mw":29,"date":"2026-03-21T20:00:00+00:00","ground":"Ramón Sánchez-Pizjuán","home":{"id":"17","name":"Sevilla FC","score":0,"formation":null,"xi":[{"id":"1211961","name":"Odysseas","num":1,"pos":null,"cap":false},{"id":"1211962","name":"Kike Salas","num":4,"pos":null,"cap":false},{"id":"1211963","name":"Suazo","num":12,"pos":null,"cap":false},{"id":"1211964","name":"Gudelj","num":6,"pos":null,"cap":true},{"id":"1211965","name":"Azpilicueta","num":3,"pos":null,"cap":false},{"id":"1211966","name":"Sow","num":20,"pos":null,"cap":false},{"id":"1211967","name":"Agoumé","num":18,"pos":null,"cap":false},{"id":"1211968","name":"Juanlu","num":16,"pos":null,"cap":false},{"id":"1211969","name":"Vargas","num":11,"pos":null,"cap":false},{"id":"1211970","name":"Maupay","num":17,"pos":null,"cap":false},{"id":"1211971","name":"Alexis","num":10,"pos":null,"cap":false}],"bench":[{"id":"1211972","name":"F. Gattoni","num":22,"pos":null,"cap":false},{"id":"1211973","name":"Jordán","num":8,"pos":null,"cap":false},{"id":"1211974","name":"Nyland","num":13,"pos":null,"cap":false},{"id":"1211975","name":"A. Castrin","num":32,"pos":null,"cap":false},{"id":"1211976","name":"Isaac","num":7,"pos":null,"cap":false},{"id":"1211977","name":"Carmona","num":2,"pos":null,"cap":false},{"id":"1211978","name":"Januzaj","num":24,"pos":null,"cap":false},{"id":"1211979","name":"B. Mendy","num":19,"pos":null,"cap":false},{"id":"1211980","name":"Nianzou","num":5,"pos":null,"cap":false},{"id":"1211981","name":"Oso","num":36,"pos":null,"cap":false},{"id":"1211982","name":"Ejuke","num":21,"pos":null,"cap":false},{"id":"1211983","name":"Akor","num":9,"pos":null,"cap":false}]},"away":{"id":"18","name":"Valencia CF","score":2,"formation":null,"xi":[{"id":"1211985","name":"Dimitrievski","num":1,"pos":null,"cap":false},{"id":"1211986","name":"Tárrega","num":5,"pos":null,"cap":false},{"id":"1211987","name":"Gayà","num":14,"pos":null,"cap":true},{"id":"1211988","name":"Nuñez","num":4,"pos":null,"cap":false},{"id":"1211989","name":"Cömert","num":24,"pos":null,"cap":false},{"id":"1211990","name":"G. Rodriguez","num":2,"pos":null,"cap":false},{"id":"1211991","name":"A. Almeida","num":10,"pos":null,"cap":false},{"id":"1211992","name":"Javi Guerra","num":8,"pos":null,"cap":false},{"id":"1211995","name":"Hugo Duro","num":9,"pos":null,"cap":false},{"id":"1211993","name":"Ramazani","num":17,"pos":null,"cap":false},{"id":"1211994","name":"L. Rioja","num":11,"pos":null,"cap":false}],"bench":[{"id":"1211996","name":"Danjuma","num":7,"pos":null,"cap":false},{"id":"1211997","name":"Diego López","num":16,"pos":null,"cap":false},{"id":"1211998","name":"Santamaria","num":22,"pos":null,"cap":false},{"id":"1211999","name":"Saravia","num":20,"pos":null,"cap":false},{"id":"1212000","name":"Raba","num":19,"pos":null,"cap":false},{"id":"1212001","name":"Beltrán","num":15,"pos":null,"cap":false},{"id":"1212002","name":"C.rivero","num":13,"pos":null,"cap":false},{"id":"1212003","name":"Sadiq","num":6,"pos":null,"cap":false},{"id":"1212004","name":"Panach","num":32,"pos":null,"cap":false},{"id":"1212005","name":"V. Abril","num":28,"pos":null,"cap":false},{"id":"1212006","name":"Pepelu","num":18,"pos":null,"cap":false},{"id":"1212007","name":"J. Vázquez","num":21,"pos":null,"cap":false}]},"events":[{"min":27,"type":"yellow","team":"home","player":"Agoumé"},{"min":37,"type":"goal","team":"away","player":"Hugo Duro"},{"min":49,"type":"goal","team":"away","player":"Ramazani"},{"min":73,"type":"yellow","team":"away","player":"Beltrán"},{"min":94,"type":"yellow","team":"home","player":"Maupay"}],"stats":[]}