{"id":"98743","mw":29,"date":"2026-03-22T20:00:00+00:00","ground":"Bernabéu","home":{"id":"15","name":"Real Madrid","score":3,"formation":null,"xi":[{"id":"1213648","name":"Lunin","num":13,"pos":null,"cap":false},{"id":"1213649","name":"Fran García","num":20,"pos":null,"cap":false},{"id":"1213650","name":"Rüdiger","num":22,"pos":null,"cap":false},{"id":"1213651","name":"Carvajal","num":2,"pos":null,"cap":true},{"id":"1213652","name":"Huijsen","num":24,"pos":null,"cap":false},{"id":"1213653","name":"Valverde","num":8,"pos":null,"cap":false},{"id":"1213654","name":"Thiago","num":45,"pos":null,"cap":false},{"id":"1213655","name":"Tchouameni","num":14,"pos":null,"cap":false},{"id":"1213656","name":"Arda Güler","num":15,"pos":null,"cap":false},{"id":"1213657","name":"Brahim","num":21,"pos":null,"cap":false},{"id":"1213658","name":"Vini Jr.","num":7,"pos":null,"cap":false}],"bench":[{"id":"1213659","name":"Gonzalo","num":16,"pos":null,"cap":false},{"id":"1213660","name":"Fran González","num":26,"pos":null,"cap":false},{"id":"1213661","name":"Mestre","num":43,"pos":null,"cap":false},{"id":"1213662","name":"Trent","num":12,"pos":null,"cap":false},{"id":"1213663","name":"Manuel Ángel","num":37,"pos":null,"cap":false},{"id":"1213664","name":"Á. Carreras","num":18,"pos":null,"cap":false},{"id":"1213665","name":"Diego Aguado","num":27,"pos":null,"cap":false},{"id":"1213666","name":"Mastantuono","num":30,"pos":null,"cap":false},{"id":"1213667","name":"Alaba","num":4,"pos":null,"cap":false},{"id":"1213668","name":"Mbappé","num":10,"pos":null,"cap":false},{"id":"1213669","name":"Bellingham","num":5,"pos":null,"cap":false},{"id":"1213670","name":"Camavinga","num":6,"pos":null,"cap":false}]},"away":{"id":"2","name":"Atlético de Madrid","score":2,"formation":null,"xi":[{"id":"1213672","name":"J. Musso","num":1,"pos":null,"cap":false},{"id":"1213673","name":"Ruggeri","num":3,"pos":null,"cap":false},{"id":"1213674","name":"Hancko","num":17,"pos":null,"cap":false},{"id":"1213675","name":"Le Normand","num":24,"pos":null,"cap":false},{"id":"1213676","name":"M. Llorente","num":14,"pos":null,"cap":false},{"id":"1213677","name":"Koke","num":6,"pos":null,"cap":true},{"id":"1213678","name":"Lookman","num":22,"pos":null,"cap":false},{"id":"1213679","name":"Giuliano","num":20,"pos":null,"cap":false},{"id":"1213680","name":"Johnny","num":5,"pos":null,"cap":false},{"id":"1213681","name":"Griezmann","num":7,"pos":null,"cap":false},{"id":"1213682","name":"J.alvarez","num":19,"pos":null,"cap":false}],"bench":[{"id":"1213683","name":"Sørloth","num":9,"pos":null,"cap":false},{"id":"1213684","name":"Julio Díaz","num":34,"pos":null,"cap":false},{"id":"1213685","name":"Lenglet","num":15,"pos":null,"cap":false},{"id":"1213686","name":"Nico","num":23,"pos":null,"cap":false},{"id":"1213687","name":"Molina","num":16,"pos":null,"cap":false},{"id":"1213688","name":"Almada","num":11,"pos":null,"cap":false},{"id":"1213689","name":"Obed Vargas","num":21,"pos":null,"cap":false},{"id":"1213690","name":"M. De Luis","num":33,"pos":null,"cap":false},{"id":"1213691","name":"Álex B.","num":10,"pos":null,"cap":false},{"id":"1213692","name":"Esquivel","num":31,"pos":null,"cap":false},{"id":"1213693","name":"J. M. Giménez","num":2,"pos":null,"cap":false}]},"events":[{"min":26,"type":"yellow","team":"away","player":"Johnny"},{"min":32,"type":"goal","team":"away","player":"Lookman"},{"min":35,"type":"yellow","team":"away","player":"Ruggeri"},{"min":51,"type":"pen","team":"home","player":"Vini Jr."},{"min":54,"type":"goal","team":"home","player":"Valverde"},{"min":60,"type":"yellow","team":"away","player":"Hancko"},{"min":62,"type":"yellow","team":"home","player":"Thiago"},{"min":65,"type":"goal","team":"away","player":"Molina"},{"min":67,"type":"yellow","team":"away","player":"M. Llorente"},{"min":71,"type":"goal","team":"home","player":"Vini Jr."},{"min":76,"type":"red","team":"home","player":"Valverde"}],"stats":[]}