{"id":"98785","mw":33,"date":"2026-04-22T18:00:00+00:00","ground":"Anoeta","home":{"id":"16","name":"Real Sociedad","score":0,"formation":null,"xi":[{"id":"1227693","name":"A. Remiro","num":1,"pos":null,"cap":false},{"id":"1227694","name":"Aritz","num":6,"pos":null,"cap":true},{"id":"1227695","name":"Jon Martin","num":31,"pos":null,"cap":false},{"id":"1227696","name":"Aihen","num":3,"pos":null,"cap":false},{"id":"1227697","name":"Caleta-Car","num":16,"pos":null,"cap":false},{"id":"1227703","name":"Take","num":14,"pos":null,"cap":false},{"id":"1227698","name":"Marin","num":15,"pos":null,"cap":false},{"id":"1227699","name":"Gorrotxa","num":4,"pos":null,"cap":false},{"id":"1227700","name":"Brais Méndez","num":23,"pos":null,"cap":false},{"id":"1227701","name":"C.soler","num":18,"pos":null,"cap":false},{"id":"1227702","name":"Oskarsson","num":9,"pos":null,"cap":false}],"bench":[{"id":"1227704","name":"Wesley","num":22,"pos":null,"cap":false},{"id":"1227705","name":"Barrene","num":7,"pos":null,"cap":false},{"id":"1227706","name":"Aramburu","num":2,"pos":null,"cap":false},{"id":"1227707","name":"Oyarzabal","num":10,"pos":null,"cap":false},{"id":"1227708","name":"Turrientes","num":8,"pos":null,"cap":false},{"id":"1227709","name":"Marrero","num":13,"pos":null,"cap":false},{"id":"1227710","name":"Zakharyan","num":21,"pos":null,"cap":false},{"id":"1227711","name":"Herrera","num":12,"pos":null,"cap":false},{"id":"1227712","name":"Karrikaburu","num":19,"pos":null,"cap":false},{"id":"1227713","name":"Sucic","num":24,"pos":null,"cap":false},{"id":"1227714","name":"Aguirre","num":46,"pos":null,"cap":false},{"id":"1227715","name":"Beitia","num":38,"pos":null,"cap":false}]},"away":{"id":"9","name":"Getafe CF","score":1,"formation":null,"xi":[{"id":"1227717","name":"David Soria","num":13,"pos":null,"cap":false},{"id":"1227718","name":"Djene","num":2,"pos":null,"cap":true},{"id":"1227719","name":"Kiko F.","num":17,"pos":null,"cap":false},{"id":"1227720","name":"Iglesias","num":21,"pos":null,"cap":false},{"id":"1227721","name":"Boselli","num":15,"pos":null,"cap":false},{"id":"1227722","name":"A. Abqar","num":3,"pos":null,"cap":false},{"id":"1227723","name":"L. Milla","num":5,"pos":null,"cap":false},{"id":"1227724","name":"Mario Martín","num":6,"pos":null,"cap":false},{"id":"1227726","name":"Arambarri","num":8,"pos":null,"cap":false},{"id":"1227727","name":"Vazquez","num":19,"pos":null,"cap":false},{"id":"1227725","name":"Satriano","num":10,"pos":null,"cap":false}],"bench":[{"id":"1227728","name":"Javi Muñoz","num":14,"pos":null,"cap":false},{"id":"1227729","name":"Nyom","num":12,"pos":null,"cap":false},{"id":"1227730","name":"Birmancevic","num":20,"pos":null,"cap":false},{"id":"1227731","name":"Liso","num":23,"pos":null,"cap":false},{"id":"1227732","name":"Riquelme","num":44,"pos":null,"cap":false},{"id":"1227733","name":"Rico","num":16,"pos":null,"cap":false},{"id":"1227734","name":"Montes","num":41,"pos":null,"cap":false},{"id":"1227735","name":"Davinchi","num":26,"pos":null,"cap":false},{"id":"1227736","name":"Alex","num":18,"pos":null,"cap":false},{"id":"1227737","name":"J. Benito","num":35,"pos":null,"cap":false},{"id":"1227738","name":"Letacek","num":1,"pos":null,"cap":false},{"id":"1227739","name":"Kamara","num":11,"pos":null,"cap":false}]},"events":[{"min":26,"type":"yellow","team":"away","player":"A. Abqar"},{"min":28,"type":"og","team":"home","player":"Gorrotxa"},{"min":30,"type":"yellow","team":"home","player":"Oskarsson"},{"min":36,"type":"yellow","team":"away","player":"Iglesias"},{"min":44,"type":"yellow","team":"home","player":"Marin"},{"min":67,"type":"yellow","team":"home","player":"Caleta-Car"},{"min":92,"type":"yellow","team":"away","player":"Boselli"},{"min":92,"type":"yellow","team":"away","player":"Nyom"},{"min":96,"type":"yellow","team":"home","player":"A. Remiro"},{"min":96,"type":"yellow","team":"away","player":"L. Milla"}],"stats":[]}