{"id":"2562024","mw":13,"date":"2025-11-30 14:05:00","ground":"London Stadium, London","home":{"id":"21","name":"West Ham United","score":0,"formation":"4-2-3-1","xi":[{"id":"84182","name":"Alphonse Areola","num":"23","pos":"Goalkeeper","cap":false},{"id":"214590","name":"Aaron Wan-Bissaka","num":"29","pos":"Defender","cap":false},{"id":"233963","name":"Konstantinos Mavropanos","num":"15","pos":"Defender","cap":false},{"id":"462116","name":"Jean-Clair Todibo","num":"25","pos":"Defender","cap":false},{"id":"613804","name":"El Hadji Malick Diouf","num":"12","pos":"Defender","cap":false},{"id":"564940","name":"Soungoutou Magassa","num":"27","pos":"Midfielder","cap":false},{"id":"490142","name":"Freddie Potts","num":"32","pos":"Midfielder","cap":false},{"id":"178186","name":"Jarrod Bowen","num":"20","pos":"Midfielder","cap":true},{"id":"224024","name":"Lucas Paquetá","num":"10","pos":"Midfielder","cap":false},{"id":"551226","name":"Mateus Fernandes","num":"18","pos":"Midfielder","cap":false},{"id":"75115","name":"Callum Wilson","num":"9","pos":"Forward","cap":false}],"bench":[{"id":"467189","name":"Mads Hermansen","num":"1","pos":"Substitute","cap":false},{"id":"158534","name":"Kyle Walker-Peters","num":"2","pos":"Substitute","cap":false},{"id":"214048","name":"Maximilian Kilman","num":"3","pos":"Substitute","cap":false},{"id":"223434","name":"Igor Julio","num":"5","pos":"Substitute","cap":false},{"id":"91889","name":"Niclas Füllkrug","num":"11","pos":"Substitute","cap":false},{"id":"577114","name":"Luis Guilherme","num":"17","pos":"Substitute","cap":false},{"id":"197024","name":"Guido Rodríguez","num":"24","pos":"Substitute","cap":false},{"id":"215439","name":"Tomás Soucek","num":"28","pos":"Substitute","cap":false},{"id":"229384","name":"Andy Irving","num":"39","pos":"Substitute","cap":false}]},"away":{"id":"14","name":"Liverpool","score":2,"formation":"4-2-3-1","xi":[{"id":"116535","name":"Alisson Becker","num":"1","pos":"Goalkeeper","cap":false},{"id":"171287","name":"Joe Gomez","num":"2","pos":"Defender","cap":false},{"id":"204716","name":"Ibrahima Konaté","num":"5","pos":"Defender","cap":false},{"id":"97032","name":"Virgil van Dijk","num":"4","pos":"Defender","cap":true},{"id":"544877","name":"Milos Kerkez","num":"6","pos":"Defender","cap":false},{"id":"441266","name":"Ryan Gravenberch","num":"38","pos":"Midfielder","cap":false},{"id":"243016","name":"Alexis Mac Allister","num":"10","pos":"Midfielder","cap":false},{"id":"424876","name":"Dominik Szoboszlai","num":"8","pos":"Midfielder","cap":false},{"id":"494595","name":"Florian Wirtz","num":"7","pos":"Midfielder","cap":false},{"id":"243298","name":"Cody Gakpo","num":"18","pos":"Midfielder","cap":false},{"id":"219168","name":"Alexander Isak","num":"9","pos":"Forward","cap":false}],"bench":[{"id":"449027","name":"Giorgi Mamardashvili","num":"25","pos":"Substitute","cap":false},{"id":"158983","name":"Wataru Endo","num":"3","pos":"Substitute","cap":false},{"id":"118748","name":"Mohamed Salah","num":"11","pos":"Substitute","cap":false},{"id":"223541","name":"Federico Chiesa","num":"14","pos":"Substitute","cap":false},{"id":"206915","name":"Curtis Jones","num":"17","pos":"Substitute","cap":false},{"id":"510663","name":"Hugo Ekitiké","num":"22","pos":"Substitute","cap":false},{"id":"122798","name":"Andy Robertson","num":"26","pos":"Substitute","cap":false},{"id":"591386","name":"Trey Nyoni","num":"42","pos":"Substitute","cap":false},{"id":"611922","name":"Rio Ngumoha","num":"73","pos":"Substitute","cap":false}]},"events":[{"min":60,"type":"goal","team":"away","player":"Alexander Isak","assist":"Cody Gakpo"},{"min":66,"type":"yellow","team":"home","player":"Soungoutou Magassa"},{"min":83,"type":"yellow","team":"home","player":"Lucas Paquetá"},{"min":84,"type":"yellow","team":"home","player":"Lucas Paquetá"},{"min":92,"type":"goal","team":"away","player":"Cody Gakpo","assist":"Joe Gomez"}],"stats":[{"label":"Possession %","home":43.8,"away":56.2,"pct":true},{"label":"Shots","home":7,"away":9,"pct":false},{"label":"Shots on target","home":0,"away":5,"pct":false},{"label":"Big chances","home":0,"away":3,"pct":false},{"label":"Corners","home":7,"away":2,"pct":false},{"label":"Offsides","home":2,"away":1,"pct":false},{"label":"Fouls","home":12,"away":14,"pct":false},{"label":"Pass accuracy %","home":80,"away":86,"pct":true},{"label":"Yellow cards","home":1,"away":0,"pct":false},{"label":"Red cards","home":1,"away":0,"pct":false},{"label":"Saves","home":3,"away":0,"pct":false}]}