{"id":"serie-a::Football_Match::550987b9107a4f0982cf975abde786fc","mw":29,"date":"2026-03-13T19:45:00Z","ground":"Olimpico - Grande Torino, Torino","home":{"id":"serie-a::Football_Team::a55dcc2058e94976b572262fc564a74c","name":"Torino","score":4,"formation":"3-4-1-2","xi":[{"id":"serie-a::Football_Player::0cc5d45eeae84da4b2c8d3335f629006","name":"Alberto Paleari","num":"1","pos":"Goalkeeper","cap":false},{"id":"serie-a::Football_Player::deaa04c0b01942838b061bf8acc34282","name":"Ardian Ismajli","num":"44","pos":"Defender","cap":false},{"id":"serie-a::Football_Player::e01f727bb7304efea37d2cc9fc152812","name":"Saúl Coco","num":"23","pos":"Defender","cap":false},{"id":"serie-a::Football_Player::c10bf0264425406d82c2909fbd66439e","name":"Enzo Ebosse","num":"77","pos":"Defender","cap":false},{"id":"serie-a::Football_Player::ffc9f90ab1494474a7e7d893e597193f","name":"Marcus Pedersen","num":"16","pos":"Defender","cap":false},{"id":"serie-a::Football_Player::afd2050ee7f64f2d80bb6ed6c702ece6","name":"Rafael Obrador Burguera","num":"33","pos":"Defender","cap":false},{"id":"serie-a::Football_Player::b91dd405c42347deb2c331fc74e97429","name":"Emirhan Ilkhan","num":"6","pos":"Midfielder","cap":false},{"id":"serie-a::Football_Player::be5ad679270341b7ade1f5046da25edd","name":"Gvidas Gineitis","num":"66","pos":"Midfielder","cap":false},{"id":"serie-a::Football_Player::8a9d45cedfdd4945978f615fc897079a","name":"Nikola Vlašić","num":"10","pos":"Midfielder","cap":false},{"id":"serie-a::Football_Player::d167c290b19a48e0a29bbf98f571152c","name":"Giovanni Simeone","num":"18","pos":"Forward","cap":false},{"id":"serie-a::Football_Player::836a85d7389346eea6090c05cc237c81","name":"Ché Adams","num":"19","pos":"Forward","cap":false}],"bench":[{"id":"serie-a::Football_Player::1521324d10634da1bdf493649696124d","name":"Franco Israel","num":"81","pos":"Goalkeeper","cap":false},{"id":"serie-a::Football_Player::8407424229094b7dbf8c8f4aca345c7b","name":"Lapo Siviero","num":"99","pos":"Goalkeeper","cap":false},{"id":"serie-a::Football_Player::3e8cfa0aff7945629977b49afe02b1c9","name":"Matteo Prati","num":"4","pos":"Midfielder","cap":false},{"id":"serie-a::Football_Player::1b963dfa250b41d5b596ef5ad7cb1379","name":"Ivan Ilić","num":"8","pos":"Midfielder","cap":false},{"id":"serie-a::Football_Player::d57de3daaf6048b1ae7ff99125188600","name":"Guillermo Maripán","num":"13","pos":"Defender","cap":false},{"id":"serie-a::Football_Player::d00c221b12c74ce08e4ef1e38addca64","name":"Tino Anjorin","num":"14","pos":"Midfielder","cap":false},{"id":"serie-a::Football_Player::69ad412c08e5413e9754af4d21250711","name":"Sandro Kulenović","num":"17","pos":"Forward","cap":false},{"id":"serie-a::Football_Player::dfcaf138f1f54ed4b9c484dad288bbe1","name":"Valentino Lazaro","num":"20","pos":"Defender","cap":false},{"id":"serie-a::Football_Player::77ebe2392746494fad62a2cc5fced9dd","name":"Cesare Casadei","num":"22","pos":"Midfielder","cap":false},{"id":"serie-a::Football_Player::4672592c583246358f920921b38f10ca","name":"Niels Patrick Nkounkou","num":"25","pos":"Defender","cap":false},{"id":"serie-a::Football_Player::0d64c3de207641ecacb222eb6a87e737","name":"Cristiano Biraghi","num":"34","pos":"Defender","cap":false},{"id":"serie-a::Football_Player::a1ee3415386144ad88b60048528e69bd","name":"Luca Marianucci","num":"35","pos":"Defender","cap":false},{"id":"serie-a::Football_Player::eac62860fcb54439a01fb719b02732dd","name":"Adrien Tamèze","num":"61","pos":"Midfielder","cap":false},{"id":"serie-a::Football_Player::fa8793423f574374b968c141faabf725","name":"Duván Zapata","num":"91","pos":"Forward","cap":false},{"id":"serie-a::Football_Player::fc2b5a269abf473795c6b6b47c736fa3","name":"Alieu Njie","num":"92","pos":"Forward","cap":false}]},"away":{"id":"serie-a::Football_Team::3294993c79b14d918ccdc78da0fb90c5","name":"Parma","score":1,"formation":"3-1-4-2","xi":[{"id":"serie-a::Football_Player::46948dee4bd54172a455ffab38485dbc","name":"Zion Suzuki","num":"31","pos":"Goalkeeper","cap":false},{"id":"serie-a::Football_Player::a01dba5f6172497b9d2f35d1cb37d24a","name":"Enrico Delprato","num":"15","pos":"Defender","cap":false},{"id":"serie-a::Football_Player::038ef975d5434ce6a293c9497fd6bb65","name":"Mariano Troilo","num":"37","pos":"Defender","cap":false},{"id":"serie-a::Football_Player::9cf5d7690d324ad2b61516ca923dbc05","name":"Alessandro Circati","num":"39","pos":"Defender","cap":false},{"id":"serie-a::Football_Player::d58bdcc9557641d3868baea58a37bdf3","name":"Emanuele Valeri","num":"14","pos":"Defender","cap":false},{"id":"serie-a::Football_Player::46afafc5e885483e954daa8e73863370","name":"Benjamin Cremaschi","num":"25","pos":"Midfielder","cap":false},{"id":"serie-a::Football_Player::ffb55f8e4e384f1d86a923e70d2629d2","name":"Christian Ordóñez","num":"24","pos":"Midfielder","cap":false},{"id":"serie-a::Football_Player::18105742a5e94cd9a0d31ac35bc60506","name":"Oliver Sørensen","num":"22","pos":"Midfielder","cap":false},{"id":"serie-a::Football_Player::4b27493789914a909a54f27f57cd3e45","name":"Mandela Keita","num":"16","pos":"Midfielder","cap":false},{"id":"serie-a::Football_Player::a4a169fd8f794bb289e98199c374e06a","name":"Mateo Pellegrino","num":"9","pos":"Forward","cap":false},{"id":"serie-a::Football_Player::526c1ebfad434e53936bb1c7e24db3a5","name":"Gabriel Strefezza","num":"7","pos":"Forward","cap":false}],"bench":[{"id":"serie-a::Football_Player::c34da415302b4416a28d463708a8ec16","name":"Edoardo Corvi","num":"40","pos":"Goalkeeper","cap":false},{"id":"serie-a::Football_Player::d24795262b354d0bb0fb4ab37dae7ced","name":"Filippo Rinaldi","num":"66","pos":"Goalkeeper","cap":false},{"id":"serie-a::Football_Player::7aa85c09d04442e0a1ace1a67c01554d","name":"Abdoulaye Ndiaye","num":"3","pos":"Defender","cap":false},{"id":"serie-a::Football_Player::c738f36256404be3830f701e8ee68149","name":"Lautaro Valenti","num":"5","pos":"Defender","cap":false},{"id":"serie-a::Football_Player::abcfe9eb7e2a40eaad6b03168cb911bb","name":"Nahuel Estévez","num":"8","pos":"Midfielder","cap":false},{"id":"serie-a::Football_Player::f1f86134a2ac4290ba546f5b014e061f","name":"Jacob Ondrejka","num":"17","pos":"Forward","cap":false},{"id":"serie-a::Football_Player::cfeb1d0545a64b06bee7773550f7198c","name":"Gaetano Oristanio","num":"21","pos":"Forward","cap":false},{"id":"serie-a::Football_Player::32277e2f0cf844a6a422442a6589b60d","name":"Nesta Elphege","num":"23","pos":"Forward","cap":false},{"id":"serie-a::Football_Player::a16050d0946f41e79f0b72cf539dd4a1","name":"Sascha Britschgi","num":"27","pos":"Defender","cap":false},{"id":"serie-a::Football_Player::98c74629e3a0424eaa0f457eb4392dab","name":"Franco Carboni","num":"29","pos":"Defender","cap":false},{"id":"serie-a::Football_Player::580e2f5d129542e2bcc9ea5436adf6a1","name":"Hans Nicolussi Caviglia","num":"41","pos":"Midfielder","cap":false},{"id":"serie-a::Football_Player::e439004a5b1145d1b8726576fe669ef2","name":"Marlon Mena","num":"63","pos":"Defender","cap":false}]},"events":[],"stats":[{"label":"Shots","home":15,"away":6,"pct":false},{"label":"Corners","home":2,"away":7,"pct":false},{"label":"Fouls","home":17,"away":13,"pct":false},{"label":"Offsides","home":4,"away":3,"pct":false},{"label":"Passes","home":409,"away":407,"pct":false},{"label":"Saves","home":1,"away":3,"pct":false},{"label":"Yellow cards","home":1,"away":3,"pct":false},{"label":"Red cards","home":0,"away":0,"pct":false}]}