{"id":"serie-a::Football_Match::60b65d10a12e427f8cfea3425e5bf46b","mw":38,"date":"2026-05-24T18:45:00Z","ground":"Ettore Giardiniero - Via Del Mare, Lecce","home":{"id":"serie-a::Football_Team::ced7bf0df3a140dfa48138311122133b","name":"Lecce","score":1,"formation":"4-2-3-1","xi":[{"id":"serie-a::Football_Player::1892b78973b5448fa477250b8a5732db","name":"Wladimiro Falcone","num":"30","pos":"Goalkeeper","cap":true},{"id":"serie-a::Football_Player::aacc54c788404b6d9945a11fef21aa1e","name":"Danilo Veiga","num":"17","pos":"Defender","cap":false},{"id":"serie-a::Football_Player::f85cb815ee9642e5a264ae703cb87da8","name":"Jamil Siebert","num":"5","pos":"Defender","cap":false},{"id":"serie-a::Football_Player::17a1eabd8e2145e89f8cec8be9a90ce9","name":"Tiago Gabriel","num":"44","pos":"Defender","cap":false},{"id":"serie-a::Football_Player::386bc75089ad468196b1372d6a4e85af","name":"Antonino Gallo","num":"25","pos":"Defender","cap":false},{"id":"serie-a::Football_Player::29de27ea145841a289fb471c08a042a8","name":"Ylber Ramadani","num":"20","pos":"Midfielder","cap":false},{"id":"serie-a::Football_Player::7187f62fdf5e476dabd0cf06ec21d580","name":"Oumar Jacky Ngom","num":"79","pos":"Midfielder","cap":false},{"id":"serie-a::Football_Player::9154d20dd59c4f3586de460f5f303d71","name":"Santiago Pierotti","num":"50","pos":"Midfielder","cap":false},{"id":"serie-a::Football_Player::585e8188ab1f452eb0225212825c051a","name":"Lassana Coulibaly","num":"29","pos":"Midfielder","cap":false},{"id":"serie-a::Football_Player::4421d3312d534346a1d4a852d63728a5","name":"Walid Cheddira","num":"99","pos":"Forward","cap":false},{"id":"serie-a::Football_Player::8ab4d9178ddb40c5b57adb7608a1f4c9","name":"Lameck Banda","num":"19","pos":"Forward","cap":false}],"bench":[{"id":"serie-a::Football_Player::8ce5c24fc6bb4d4f846a4ad8dbb573db","name":"Christian Früchtl","num":"1","pos":"Goalkeeper","cap":false},{"id":"serie-a::Football_Player::c3759dc16f2f41bbbb331b03f2e38060","name":"Jasper Samooja","num":"32","pos":"Goalkeeper","cap":false},{"id":"serie-a::Football_Player::93890966ccb24dbf94485489f23f81ea","name":"Corrie Ndaba","num":"3","pos":"Defender","cap":false},{"id":"serie-a::Football_Player::2241d16b749246698712e2d0f18ce48c","name":"Kialonda Gaspar","num":"4","pos":"Defender","cap":false},{"id":"serie-a::Football_Player::9240e5e091274f12922500faa534ce95","name":"Álex Sala","num":"6","pos":"Midfielder","cap":false},{"id":"serie-a::Football_Player::c05c5195bc064a1fbfd39b72715018b2","name":"Sadik Fofana","num":"8","pos":"Midfielder","cap":false},{"id":"serie-a::Football_Player::6b65d68dbfb64a4abe4ccc3915c8509d","name":"Nikola Štulić","num":"9","pos":"Forward","cap":false},{"id":"serie-a::Football_Player::ab36af56054945ef8f56a3b54cd323c5","name":"Konan N’Dri","num":"11","pos":"Forward","cap":false},{"id":"serie-a::Football_Player::d25925522f2e4903812479ba5ece8926","name":"Matías Pérez","num":"13","pos":"Defender","cap":false},{"id":"serie-a::Football_Player::aa13ef84519b43358627a26804914d9e","name":"Þórir Helgason","num":"14","pos":"Midfielder","cap":false},{"id":"serie-a::Football_Player::4b3e49a8789d4cbc84e0f85cfe5752b4","name":"Omri Gandelman","num":"16","pos":"Midfielder","cap":false},{"id":"serie-a::Football_Player::635e82f4100e46138e16480d1fdc5b70","name":"Gaby Jean","num":"18","pos":"Defender","cap":false},{"id":"serie-a::Football_Player::236541094aea443b92ea9ae2520bdd52","name":"Francesco Camarda","num":"22","pos":"Forward","cap":false},{"id":"serie-a::Football_Player::68347a9ebb3c4e27b5208dc818bc2bdf","name":"Olaf Gorter","num":"28","pos":"Midfielder","cap":false},{"id":"serie-a::Football_Player::bb4cf7e7223046cba660e579c9ade183","name":"Filip Marchwiński","num":"36","pos":"Midfielder","cap":false}]},"away":{"id":"serie-a::Football_Team::8c7aa94d22f44738951748e2ccdf319a","name":"Genoa","score":0,"formation":"3-5-1-1","xi":[{"id":"serie-a::Football_Player::03ea7d3b17b74069830746c24db1de69","name":"Nicola Leali","num":"1","pos":"Goalkeeper","cap":false},{"id":"serie-a::Football_Player::4aceacf99c214eacbf37b81beb326488","name":"Aarón Martín","num":"3","pos":"Defender","cap":false},{"id":"serie-a::Football_Player::d56eec021a0e467db06e5958d5c37e41","name":"Nils Zätterström","num":"13","pos":"Defender","cap":false},{"id":"serie-a::Football_Player::50f786bf0927432c9ee1d36704a91106","name":"Sebastian Otoa","num":"34","pos":"Defender","cap":false},{"id":"serie-a::Football_Player::65bb7b8d02084d858daeba0cff0cc4eb","name":"Alessandro Marcandalli","num":"27","pos":"Defender","cap":false},{"id":"serie-a::Football_Player::9cc9a483cb14471f80f9c047e821308d","name":"Stefano Sabelli","num":"20","pos":"Defender","cap":false},{"id":"serie-a::Football_Player::e6fa5c6e91694adcb60f8b6d359cf11c","name":"Patrizio Masini","num":"73","pos":"Midfielder","cap":false},{"id":"serie-a::Football_Player::ebc8da84f5ab44e28aeccc9bedd71b2a","name":"Morten Frendrup","num":"32","pos":"Midfielder","cap":true},{"id":"serie-a::Football_Player::dbd53bdc4ffe446da33ce7774384da90","name":"Mikael Ellertsson","num":"77","pos":"Midfielder","cap":false},{"id":"serie-a::Football_Player::4fbfb165723441d9a09b3e912770ad90","name":"Alexsandro Amorim","num":"4","pos":"Midfielder","cap":false},{"id":"serie-a::Football_Player::a4138ae6bf454cbd97f0a5ce554de3b5","name":"Lorenzo Colombo","num":"29","pos":"Forward","cap":false}],"bench":[{"id":"serie-a::Football_Player::4cf1b0e719d44e95aa0f4ca057f0f025","name":"Justin Bijlow","num":"16","pos":"Goalkeeper","cap":false},{"id":"serie-a::Football_Player::308ee64855794d61811119f70f5f018e","name":"Daniele Sommariva","num":"39","pos":"Goalkeeper","cap":false},{"id":"serie-a::Football_Player::48bbf1a2c4494bb0b02d0a49eb431c98","name":"Brooke Norton-Cuffy","num":"15","pos":"Defender","cap":false},{"id":"serie-a::Football_Player::8e6bacec24e049f9b1ae813a030ebc96","name":"Marco Romano","num":"19","pos":"Forward","cap":false},{"id":"serie-a::Football_Player::ac9814fb4e4245378d64a972b9fd3199","name":"Johan Vásquez","num":"22","pos":"Defender","cap":false},{"id":"serie-a::Football_Player::0922b2395d2f480e863bb4ac95a798e7","name":"Filippo Carbone","num":"71","pos":"Midfielder","cap":false},{"id":"serie-a::Football_Player::e04cf0452d6c47e5a2a0e8a9f69b93c1","name":"Mamedi Doucoure","num":"74","pos":"Defender","cap":false},{"id":"serie-a::Football_Player::38b63b8ba7a142afaad360ceb91bac88","name":"Gaël Lafont","num":"75","pos":"Midfielder","cap":false},{"id":"serie-a::Football_Player::81c419a50cb84df4ba0a4a848e44e777","name":"Jacopo Grossi","num":"80","pos":"Midfielder","cap":false},{"id":"serie-a::Football_Player::cb2b2e64019645509c11072e1aebb56a","name":"Elia Spicuglia","num":"97","pos":"Forward","cap":false},{"id":"serie-a::Football_Player::969213be1be7493781f215b4bbfd0887","name":"Wedtoin Latif Ouedraogo","num":"99","pos":"Forward","cap":false}]},"events":[],"stats":[{"label":"Possession %","home":34,"away":66,"pct":true},{"label":"Shots","home":8,"away":8,"pct":false},{"label":"Corners","home":1,"away":6,"pct":false},{"label":"Fouls","home":11,"away":6,"pct":false},{"label":"Offsides","home":4,"away":1,"pct":false},{"label":"Passes","home":268,"away":528,"pct":false},{"label":"Saves","home":1,"away":3,"pct":false},{"label":"Yellow cards","home":2,"away":0,"pct":false},{"label":"Red cards","home":0,"away":0,"pct":false}]}