{"id":"serie-a::Football_Match::8af56bd23847453b93ca14b453b0f524","mw":9,"date":"2025-10-29T19:45:00Z","ground":"Luigi Ferraris, Genova","home":{"id":"serie-a::Football_Team::8c7aa94d22f44738951748e2ccdf319a","name":"Genoa","score":0,"formation":"4-2-3-1","xi":[{"id":"serie-a::Football_Player::03ea7d3b17b74069830746c24db1de69","name":"Nicola Leali","num":"1","pos":"Goalkeeper","cap":false},{"id":"serie-a::Football_Player::ac9814fb4e4245378d64a972b9fd3199","name":"Johan Vásquez","num":"22","pos":"Defender","cap":false},{"id":"serie-a::Football_Player::816125e2bba042b38c44a6bb8b005f83","name":"Leo Østigård","num":"5","pos":"Defender","cap":false},{"id":"serie-a::Football_Player::48bbf1a2c4494bb0b02d0a49eb431c98","name":"Brooke Norton-Cuffy","num":"15","pos":"Defender","cap":false},{"id":"serie-a::Football_Player::4aceacf99c214eacbf37b81beb326488","name":"Aarón Martín","num":"3","pos":"Defender","cap":false},{"id":"serie-a::Football_Player::dbd53bdc4ffe446da33ce7774384da90","name":"Mikael Ellertsson","num":"77","pos":"Midfielder","cap":false},{"id":"serie-a::Football_Player::a4af8f3465e44cefbe9617f9c576691b","name":"Ruslan Malinovskyi","num":"17","pos":"Midfielder","cap":false},{"id":"serie-a::Football_Player::e6fa5c6e91694adcb60f8b6d359cf11c","name":"Patrizio Masini","num":"73","pos":"Midfielder","cap":false},{"id":"serie-a::Football_Player::42e0a8cf9e1e4cd0a1830d1d7b09f934","name":"Jeff Ekhator","num":"21","pos":"Forward","cap":false},{"id":"serie-a::Football_Player::2681452588b14a15a9aa5afe6fab05d3","name":"Maxwel Cornet","num":"70","pos":"Forward","cap":false},{"id":"serie-a::Football_Player::9a1ea729ff9e4ac092602eb71e9c2a67","name":"V. Carboni","num":"23","pos":"Forward","cap":false}],"bench":[{"id":"serie-a::Football_Player::a7f3917b59744fcbb169a2adb6f4d2e7","name":"Benjamin Siegrist","num":"31","pos":"Goalkeeper","cap":false},{"id":"serie-a::Football_Player::308ee64855794d61811119f70f5f018e","name":"Daniele Sommariva","num":"39","pos":"Goalkeeper","cap":false},{"id":"serie-a::Football_Player::f3670f8a13ba4c38a58d8f59eda2e1b0","name":"Morten Thorsby","num":"2","pos":"Midfielder","cap":false},{"id":"serie-a::Football_Player::6a33b5176e6b46da8e921a0e2996a573","name":"Vitinha","num":"9","pos":"Forward","cap":false},{"id":"serie-a::Football_Player::a5664d63c9d944e2be3e08a3aa1d4d5b","name":"Junior Messias","num":"10","pos":"Forward","cap":false},{"id":"serie-a::Football_Player::b935d80dda174738ab539b7d73b71a16","name":"Albert Grønbæk","num":"11","pos":"Midfielder","cap":false},{"id":"serie-a::Football_Player::3e3618a7ee924889973db5ff58423c2b","name":"Jean Onana","num":"14","pos":"Forward","cap":false},{"id":"serie-a::Football_Player::31928c74a5ca45fea7d419b29e526adc","name":"Caleb Ekuban","num":"18","pos":"Forward","cap":false},{"id":"serie-a::Football_Player::9cc9a483cb14471f80f9c047e821308d","name":"Stefano Sabelli","num":"20","pos":"Defender","cap":false},{"id":"serie-a::Football_Player::65bb7b8d02084d858daeba0cff0cc4eb","name":"Alessandro Marcandalli","num":"27","pos":"Defender","cap":false},{"id":"serie-a::Football_Player::a4138ae6bf454cbd97f0a5ce554de3b5","name":"Lorenzo Colombo","num":"29","pos":"Forward","cap":false},{"id":"serie-a::Football_Player::4f99b059e04c47dc9feb28b23e95f252","name":"Hugo Cuenca","num":"30","pos":"Forward","cap":false},{"id":"serie-a::Football_Player::ebc8da84f5ab44e28aeccc9bedd71b2a","name":"Morten Frendrup","num":"32","pos":"Midfielder","cap":false},{"id":"serie-a::Football_Player::f0f15f171e034b32a0a4559ee10219cf","name":"Seydou Fini","num":"40","pos":"Forward","cap":false},{"id":"serie-a::Football_Player::cc52adc5bbc24b01b26fb63196963491","name":"Lorenzo Venturino","num":"76","pos":"Forward","cap":false}]},"away":{"id":"serie-a::Football_Team::920da3c6b91d4cf69b2f1448c8a71c96","name":"Cremonese","score":2,"formation":"3-5-2","xi":[{"id":"serie-a::Football_Player::ffc8be5bd4e749d0b24674083abab469","name":"Emil Audero","num":"1","pos":"Goalkeeper","cap":false},{"id":"serie-a::Football_Player::528463bd1ae34632b21700b2f1a4290c","name":"Filippo Terracciano","num":"24","pos":"Defender","cap":false},{"id":"serie-a::Football_Player::2b979996a62e42b7b29bbc5021db165d","name":"Federico Baschirotto","num":"6","pos":"Defender","cap":false},{"id":"serie-a::Football_Player::684ed44f98154c089715f064f4023da7","name":"M. Bianchetti","num":"15","pos":"Defender","cap":false},{"id":"serie-a::Football_Player::aa1362df3327444797ed07f5ff55bfd0","name":"Tommaso Barbieri","num":"4","pos":"Defender","cap":false},{"id":"serie-a::Football_Player::79c109c187ce4f7cbf763e5b9484319e","name":"Romano Floriani M.","num":"22","pos":"Defender","cap":false},{"id":"serie-a::Football_Player::bd51deb9de4a486dbaa8f1544cad3e31","name":"Martín Payero","num":"32","pos":"Midfielder","cap":false},{"id":"serie-a::Football_Player::5395422c0fce40fba80082e4dc17ae13","name":"Warren Bondo","num":"38","pos":"Midfielder","cap":false},{"id":"serie-a::Football_Player::fb2b044ea2c641fdaf6dbdc46a8526b6","name":"Jari Vandeputte","num":"27","pos":"Midfielder","cap":false},{"id":"serie-a::Football_Player::d72bcb4304da42e58f04bcf31478a26d","name":"Jamie Vardy","num":"10","pos":"Forward","cap":false},{"id":"serie-a::Football_Player::50816a645bb841f384fc015e69e2374c","name":"Federico Bonazzoli","num":"90","pos":"Forward","cap":false}],"bench":[{"id":"serie-a::Football_Player::adb3802917f84f18b2d899e1cc681700","name":"Marco Silvestri","num":"16","pos":"Goalkeeper","cap":false},{"id":"serie-a::Football_Player::b951edc16d794b30a47216f1a1fbba0e","name":"Lapo Nava","num":"69","pos":"Goalkeeper","cap":false},{"id":"serie-a::Football_Player::2bee752bd6864cda812f7412a5c488d6","name":"Dennis Johnsen","num":"11","pos":"Forward","cap":false},{"id":"serie-a::Football_Player::03c05df97b77421da203188cbc791440","name":"Jeremy Sarmiento","num":"19","pos":"Midfielder","cap":false},{"id":"serie-a::Football_Player::e2988ee3555b45dd8ab054fc8516212a","name":"Franco Vázquez","num":"20","pos":"Forward","cap":false},{"id":"serie-a::Football_Player::f2a038aaa96148e3976dd85dfae27efe","name":"Federico Ceccherini","num":"23","pos":"Defender","cap":false},{"id":"serie-a::Football_Player::360b542865f3416281aaa54779f024a3","name":"Mikayil Faye","num":"30","pos":"Defender","cap":false},{"id":"serie-a::Football_Player::0b0d4590a66644bda6795790af9173f0","name":"Dachi Lordkipanidze","num":"48","pos":"Midfielder","cap":false},{"id":"serie-a::Football_Player::1caac65130604f188756f92f6b6c76b9","name":"Francesco Folino","num":"55","pos":"Defender","cap":false},{"id":"serie-a::Football_Player::4677e9cabbbb4022a03989de2a097183","name":"Adrian Lickunas","num":"84","pos":"Midfielder","cap":false}]},"events":[],"stats":[{"label":"Possession %","home":53,"away":47,"pct":true},{"label":"Shots","home":16,"away":11,"pct":false},{"label":"Corners","home":7,"away":3,"pct":false},{"label":"Fouls","home":16,"away":13,"pct":false},{"label":"Offsides","home":3,"away":0,"pct":false},{"label":"Passes","home":393,"away":346,"pct":false},{"label":"Saves","home":2,"away":1,"pct":false},{"label":"Yellow cards","home":3,"away":1,"pct":false},{"label":"Red cards","home":0,"away":0,"pct":false}]}