{"id":"serie-a::Football_Match::a0a3a2411f0149ca9ef52fd32ecc41c0","mw":13,"date":"2025-11-29T14:00:00Z","ground":"Ennio Tardini, Parma","home":{"id":"serie-a::Football_Team::3294993c79b14d918ccdc78da0fb90c5","name":"Parma","score":0,"formation":"3-5-2","xi":[{"id":"serie-a::Football_Player::c34da415302b4416a28d463708a8ec16","name":"Edoardo Corvi","num":"40","pos":"Goalkeeper","cap":false},{"id":"serie-a::Football_Player::d58bdcc9557641d3868baea58a37bdf3","name":"Emanuele Valeri","num":"14","pos":"Defender","cap":false},{"id":"serie-a::Football_Player::a16050d0946f41e79f0b72cf539dd4a1","name":"Sascha Britschgi","num":"27","pos":"Defender","cap":false},{"id":"serie-a::Football_Player::a01dba5f6172497b9d2f35d1cb37d24a","name":"Enrico Delprato","num":"15","pos":"Defender","cap":false},{"id":"serie-a::Football_Player::038ef975d5434ce6a293c9497fd6bb65","name":"Mariano Troilo","num":"37","pos":"Defender","cap":false},{"id":"serie-a::Football_Player::c738f36256404be3830f701e8ee68149","name":"Lautaro Valenti","num":"5","pos":"Defender","cap":false},{"id":"serie-a::Football_Player::18105742a5e94cd9a0d31ac35bc60506","name":"Oliver Sørensen","num":"22","pos":"Midfielder","cap":false},{"id":"serie-a::Football_Player::4b27493789914a909a54f27f57cd3e45","name":"Mandela Keita","num":"16","pos":"Midfielder","cap":false},{"id":"serie-a::Football_Player::bfe627dce98446ed9ce53fa9afaf479b","name":"Adrián Bernabé","num":"10","pos":"Midfielder","cap":false},{"id":"serie-a::Football_Player::a4a169fd8f794bb289e98199c374e06a","name":"Mateo Pellegrino","num":"9","pos":"Forward","cap":false},{"id":"serie-a::Football_Player::4919025f871840d199d459a2c636266e","name":"Patrick Cutrone","num":"32","pos":"Forward","cap":false}],"bench":[{"id":"serie-a::Football_Player::42fb1259353945f39245f47362eae798","name":"Vicente Guaita","num":"13","pos":"Goalkeeper","cap":false},{"id":"serie-a::Football_Player::d24795262b354d0bb0fb4ab37dae7ced","name":"Filippo Rinaldi","num":"66","pos":"Goalkeeper","cap":false},{"id":"serie-a::Football_Player::5908e4c64e5a46f1a6c846810586e624","name":"Adrian Benedyczak","num":"7","pos":"Forward","cap":false},{"id":"serie-a::Football_Player::abcfe9eb7e2a40eaad6b03168cb911bb","name":"Nahuel Estévez","num":"8","pos":"Midfielder","cap":false},{"id":"serie-a::Football_Player::50da604b3a694f0581a2066168c2988b","name":"Pontus Almqvist","num":"11","pos":"Forward","cap":false},{"id":"serie-a::Football_Player::f1f86134a2ac4290ba546f5b014e061f","name":"Jacob Ondrejka","num":"17","pos":"Forward","cap":false},{"id":"serie-a::Football_Player::95113df1d4494b4cbf1e7f378d740782","name":"Mathias Løvik","num":"18","pos":"Defender","cap":false},{"id":"serie-a::Football_Player::37e258380dab45e387ebbc299a2c0182","name":"Tjas Begic","num":"19","pos":"Forward","cap":false},{"id":"serie-a::Football_Player::cfeb1d0545a64b06bee7773550f7198c","name":"Gaetano Oristanio","num":"21","pos":"Forward","cap":false},{"id":"serie-a::Football_Player::064aed514b584e55a8fcefb1be3db5eb","name":"Hernani","num":"23","pos":"Midfielder","cap":false},{"id":"serie-a::Football_Player::ffb55f8e4e384f1d86a923e70d2629d2","name":"Christian Ordóñez","num":"24","pos":"Midfielder","cap":false},{"id":"serie-a::Football_Player::46afafc5e885483e954daa8e73863370","name":"Benjamin Cremaschi","num":"25","pos":"Midfielder","cap":false},{"id":"serie-a::Football_Player::79e8e49205aa488b8f48057e10ae5f94","name":"Milan Djuric","num":"30","pos":"Forward","cap":false},{"id":"serie-a::Football_Player::2a72c273fe2649519da24e6fef05e666","name":"Nicolas Trabucchi","num":"63","pos":"Defender","cap":false},{"id":"serie-a::Football_Player::5f7b8516e8e64775817ed94a57cf2d7e","name":"Bernardo Conde","num":"70","pos":"Defender","cap":false}]},"away":{"id":"serie-a::Football_Team::630b1e3631db42498d1b7bc94595c5e0","name":"Udinese","score":2,"formation":"3-5-2","xi":[{"id":"serie-a::Football_Player::577277231cb84394a7d96c70a11a528f","name":"Maduka Okoye","num":"40","pos":"Goalkeeper","cap":false},{"id":"serie-a::Football_Player::1a115e96dce24288ae6ac16522b66ceb","name":"A. Zanoli","num":"59","pos":"Defender","cap":false},{"id":"serie-a::Football_Player::2c1de35b4eba480dbcd4e21a4cde2c88","name":"Jordan Zemura","num":"33","pos":"Defender","cap":false},{"id":"serie-a::Football_Player::ab6119135bdc4a09b35d54fab9e6fa92","name":"N. Bertola","num":"13","pos":"Defender","cap":false},{"id":"serie-a::Football_Player::700f9b23586149c6a32011198f8e928a","name":"Christian Kabasele","num":"27","pos":"Defender","cap":false},{"id":"serie-a::Football_Player::aa46c1e9504d4070876a364bc69fc470","name":"Oumar Solet","num":"28","pos":"Defender","cap":false},{"id":"serie-a::Football_Player::450a3f00ad6b48838ecae9c93a3abf01","name":"Jakub Piotrowski","num":"24","pos":"Midfielder","cap":false},{"id":"serie-a::Football_Player::75e8a5f9f7c54239aaf5c7620816ca7a","name":"Jesper Karlström","num":"8","pos":"Midfielder","cap":false},{"id":"serie-a::Football_Player::cd9708fcf981489e939152ec78f997c2","name":"Arthur Atta","num":"14","pos":"Midfielder","cap":false},{"id":"serie-a::Football_Player::bceddc37986049e09f271927bd712727","name":"Keinan Davis","num":"9","pos":"Forward","cap":false},{"id":"serie-a::Football_Player::f7bce030bb504b87b9411db54d75480f","name":"Nicolò Zaniolo","num":"10","pos":"Forward","cap":false}],"bench":[{"id":"serie-a::Football_Player::c66a8f0dd6dd43e6b06c5a4890d52a12","name":"Razvan Sava","num":"90","pos":"Goalkeeper","cap":false},{"id":"serie-a::Football_Player::f42dc8a471d44f2d8cb4a23c2cb0fefc","name":"Daniele Padelli","num":"93","pos":"Goalkeeper","cap":false},{"id":"serie-a::Football_Player::50a60abf290e4880afe7411c15616fb2","name":"Saba Goglichidze","num":"2","pos":"Defender","cap":false},{"id":"serie-a::Football_Player::4f65b66648584493baf8b6a7a025413b","name":"Sandi Lovrić","num":"4","pos":"Midfielder","cap":false},{"id":"serie-a::Football_Player::5931a8de6cc3493ebdaa0b4c30758add","name":"Oier Zarraga","num":"6","pos":"Midfielder","cap":false},{"id":"serie-a::Football_Player::1c89b95ec197444798e975aede089c2c","name":"Idrissa Gueye","num":"7","pos":"Forward","cap":false},{"id":"serie-a::Football_Player::ce65d2c930994c68973373b77f85b2fa","name":"Vakoun Bayo","num":"15","pos":"Forward","cap":false},{"id":"serie-a::Football_Player::663b54dec4a14f3bb02e940c87a699c8","name":"Matteo Palma","num":"16","pos":"Defender","cap":false},{"id":"serie-a::Football_Player::74e3b0dfd49c49e582c6d804539367e7","name":"Iker Bravo","num":"17","pos":"Forward","cap":false},{"id":"serie-a::Football_Player::4c54d51902bb49dbb90c4c01a3d955a2","name":"Adam Buksa","num":"18","pos":"Forward","cap":false},{"id":"serie-a::Football_Player::52d5b4022e8e431aa4b4c8983843965b","name":"Kingsley Ehizibue","num":"19","pos":"Defender","cap":false},{"id":"serie-a::Football_Player::99bc11d4d74d4fbc8b911367fdc47001","name":"Abdoulaye Camara","num":"29","pos":"Midfielder","cap":false},{"id":"serie-a::Football_Player::e8f6079ece014914adab3caf2e98babb","name":"Jurgen Ekkelenkamp","num":"32","pos":"Midfielder","cap":false},{"id":"serie-a::Football_Player::f97b651b46874386ab92d0e88d27e490","name":"Lennon Miller","num":"38","pos":"Midfielder","cap":false},{"id":"serie-a::Football_Player::9d07b4ef7bea4aae9e85d8b094ee251f","name":"Rui Modesto","num":"77","pos":"Defender","cap":false}]},"events":[],"stats":[{"label":"Possession %","home":51,"away":49,"pct":true},{"label":"Shots","home":16,"away":12,"pct":false},{"label":"Corners","home":5,"away":9,"pct":false},{"label":"Fouls","home":6,"away":19,"pct":false},{"label":"Offsides","home":2,"away":1,"pct":false},{"label":"Passes","home":347,"away":354,"pct":false},{"label":"Saves","home":3,"away":2,"pct":false},{"label":"Yellow cards","home":1,"away":2,"pct":false},{"label":"Red cards","home":1,"away":0,"pct":false}]}